numpy4/ADS_DataCleaning.py
numpy4/ADS_SMOTE.py
numpy4/ADS_inferentialStats.py
numpy4/ADS_outlierDetection.py
numpy4/ADS_stats.py
numpy4/ADS_superviseEval.py
numpy4/ADS_timeSeries.py
numpy4/ADS_unsuperviseEval.py
numpy4/ADS_visualization.py
numpy4/Cnn.py
numpy4/DC_Bankers.py
numpy4/DC_Berkley.py
numpy4/DC_Bully.py
numpy4/DC_RaymondTree.py
numpy4/DC_RicartAgrawala.py
numpy4/DC_gc.py
numpy4/DC_globalAvg.py
numpy4/DC_ipc.py
numpy4/DC_loadBalancing.py
numpy4/DC_multithreading.py
numpy4/Rnn-lstm.py
numpy4/__init__.py
numpy4/adam.py
numpy4/autoencoder.py
numpy4/fnn-perceptron.py
numpy4/mc-culloch-pitt.py
numpy4/mini-batch-gd.py
numpy4/momentum-gd.py
numpy4/nestrov-gd.py
numpy4/optimization-adagrad-gd.py
numpy4/optimization-stocastic-gd.py
numpy4/optimization-vanilla-gd.py
numpy4/rms.py
numpy4/sma_10_community_prac_exam.py
numpy4/sma_1_topic_keyword_prac_exam.py
numpy4/sma_2_location_prac_exam.py
numpy4/sma_3_trends_prac_exam.py
numpy4/sma_4_hashtag_prac_exam.py
numpy4/sma_5_sentiment_prac_exam.py
numpy4/sma_6_user_engagement_prac_exam.py
numpy4/sma_7_eda_visualization_prac_exam (1).py
numpy4/sma_7_eda_visualization_prac_exam.py
numpy4/sma_8_brand_prac_exam.py
numpy4/sma_9_competitor_prac_exam.py
numpy4-0.7.dist-info/METADATA
numpy4-0.7.dist-info/WHEEL
numpy4-0.7.dist-info/top_level.txt
numpy4-0.7.dist-info/RECORD
